no_global_nonlocal_vars/__init__.py
no_global_nonlocal_vars/no_global_nonlocal_vars.py
no_global_nonlocal_vars-0.0.2.dist-info/LICENSE
no_global_nonlocal_vars-0.0.2.dist-info/METADATA
no_global_nonlocal_vars-0.0.2.dist-info/WHEEL
no_global_nonlocal_vars-0.0.2.dist-info/top_level.txt
no_global_nonlocal_vars-0.0.2.dist-info/RECORD
