Metadata-Version: 2.1
Name: no-global-nonlocal-vars
Version: 0.0.2
Summary: Function decorator that ensures that no global and no nonlocal variables are used, making Jupyter notebooks much safer
Home-page: https://github.com/tylerlum/no_global_nonlocal_vars
Author: Tyler Lum
Author-email: tylergwlum@gmail.com
Keywords: python,jupyter,notebook,decorator,global,nonlocal
Classifier: Intended Audience :: Developers
Classifier: Topic :: Utilities
Classifier: License :: OSI Approved :: MIT License
Classifier: Programming Language :: Python :: 3
License-File: LICENSE
